pyGrad2Surf/__init__.py
pyGrad2Surf/difflocal.py
pyGrad2Surf/g2s.py
pyGrad2Surf-0.1.0.dist-info/DESCRIPTION.rst
pyGrad2Surf-0.1.0.dist-info/METADATA
pyGrad2Surf-0.1.0.dist-info/RECORD
pyGrad2Surf-0.1.0.dist-info/WHEEL
pyGrad2Surf-0.1.0.dist-info/metadata.json
pyGrad2Surf-0.1.0.dist-info/top_level.txt
