Metadata-Version: 2.0
Name: pyGrad2Surf
Version: 0.1.0
Summary: A python translation of the Grad2Surf software provided by Harker & O'Leary
Home-page: https://github.com/cjordan/pyGrad2Surf
Author: Christopher Jordan
Author-email: christopherjordan87@gmail.com
License: MIT
Keywords: signal processing
Platform: UNKNOWN
Requires-Dist: numpy
Requires-Dist: scipy
